puzzle15Gym/__init__.py
puzzle15Gym/puzzle15_env.py
puzzle15Gym/register_env.py
puzzle15gym-1.0.3.dist-info/licenses/LICENSE
puzzle15gym-1.0.3.dist-info/METADATA
puzzle15gym-1.0.3.dist-info/WHEEL
puzzle15gym-1.0.3.dist-info/top_level.txt
puzzle15gym-1.0.3.dist-info/RECORD
