Metadata-Version: 2.4
Name: puzzle15Gym
Version: 1.0.3
Summary: A custom AI Gym environment for the sliding block puzzle game
Author-email: Evaldas Visockas <developersediary@gmail.com>
License: GPL-3.0-or-later 
Project-URL: Repository, https://github.com/EvalVis/Puzzle15Gym
Requires-Python: >=3.12
License-File: LICENSE
Requires-Dist: gymnasium>=1.1.1
Requires-Dist: numpy>=2.2.3
Requires-Dist: matplotlib>=3.10.1
Requires-Dist: puzzle15>=1.0.1
Dynamic: license-file
